README.txt
setup.cfg
setup.py
collective/__init__.py
collective.contentsync.egg-info/PKG-INFO
collective.contentsync.egg-info/SOURCES.txt
collective.contentsync.egg-info/dependency_links.txt
collective.contentsync.egg-info/entry_points.txt
collective.contentsync.egg-info/namespace_packages.txt
collective.contentsync.egg-info/not-zip-safe
collective.contentsync.egg-info/requires.txt
collective.contentsync.egg-info/top_level.txt
collective/contentsync/TODO.txt
collective/contentsync/__init__.py
collective/contentsync/configure.zcml
collective/contentsync/eventhandlers.py
collective/contentsync/events.py
collective/contentsync/interfaces.py
collective/contentsync/profiles.zcml
collective/contentsync/browser/__init__.py
collective/contentsync/browser/configure.zcml
collective/contentsync/browser/interfaces.py
collective/contentsync/browser/progress.pt
collective/contentsync/browser/sync_form.pt
collective/contentsync/browser/util.py
collective/contentsync/browser/utilities.py
collective/contentsync/browser/views.py
collective/contentsync/browser/resources/__init__.py
collective/contentsync/browser/resources/configure.zcml
collective/contentsync/browser/resources/progress_iframe.pt
collective/contentsync/profiles/default/actions.xml
collective/contentsync/tests/ContentSyncTestCase.py
collective/contentsync/tests/__init__.py
collective/contentsync/tests/test_sync.py
docs/HISTORY.txt