Metadata-Version: 1.0
Name: collective.contentsync
Version: 1.01
Summary: Synchronize a container with a master container
Home-page: UNKNOWN
Author: Hedley Roos
Author-email: hedley@upfrontsystems.co.za
License: GPL
Platform: UNKNOWN
Classifier: Framework :: Plone
Classifier: Framework :: Zope2
Classifier: Programming Language :: Python
